./.gitignore
./PKG-INFO
./README.md
./flow_core.py
./mcp_server.py
./pyproject.toml
./uv.lock
./framework/DEVELOPMENT_FRAMEWORK.md
./framework/EXAMPLE_PLAN.md
./framework/SLASH_COMMANDS.md
mcp_server_flow-1.2.16.dist-info/METADATA
mcp_server_flow-1.2.16.dist-info/WHEEL
mcp_server_flow-1.2.16.dist-info/entry_points.txt
mcp_server_flow-1.2.16.dist-info/RECORD
