Metadata-Version: 2.4
Name: mcp-server-flow
Version: 1.2.16
Summary: MCP server for Flow Framework - Spec-driven iterative development methodology
Author-email: Liad Goren <liadgoren@example.com>
Requires-Python: >=3.10
Requires-Dist: fastmcp>=2.0.0
